dagflow/__init__.py
dagflow/bundles/__init__.py
dagflow/bundles/file_reader.py
dagflow/bundles/load_array.py
dagflow/bundles/load_graph.py
dagflow/bundles/load_hist.py
dagflow/bundles/load_parameters.py
dagflow/bundles/load_record.py
dagflow/bundles/make_y_parameters_for_x.py
dagflow/core/__init__.py
dagflow/core/data_descriptor.py
dagflow/core/edges.py
dagflow/core/exception.py
dagflow/core/flags_descriptor.py
dagflow/core/graph.py
dagflow/core/graph_base.py
dagflow/core/input.py
dagflow/core/input_strategy.py
dagflow/core/iter.py
dagflow/core/iterators.py
dagflow/core/labels.py
dagflow/core/make_fcn.py
dagflow/core/meta_node.py
dagflow/core/node.py
dagflow/core/node_base.py
dagflow/core/output.py
dagflow/core/storage.py
dagflow/core/types.py
dagflow/core/type_functions/__init__.py
dagflow/core/type_functions/axes_type_functions.py
dagflow/core/type_functions/copy_type_functions.py
dagflow/core/type_functions/input_type_functions.py
dagflow/core/type_functions/output_type_functions.py
dagflow/core/type_functions/tools_for_type_functions.py
dagflow/export/__init__.py
dagflow/export/to_root.py
dagflow/lib/__init__.py
dagflow/lib/arithmetic.py
dagflow/lib/exponential.py
dagflow/lib/trigonometry.py
dagflow/lib/abstract/__init__.py
dagflow/lib/abstract/block_to_one_node.py
dagflow/lib/abstract/many_to_one_node.py
dagflow/lib/abstract/one_to_one_node.py
dagflow/lib/axis/__init__.py
dagflow/lib/axis/bin_center.py
dagflow/lib/axis/mesh_to_edges.py
dagflow/lib/calculus/__init__.py
dagflow/lib/calculus/jacobian.py
dagflow/lib/common/__init__.py
dagflow/lib/common/array.py
dagflow/lib/common/cache.py
dagflow/lib/common/concatenation.py
dagflow/lib/common/copy.py
dagflow/lib/common/dummy.py
dagflow/lib/common/proxy.py
dagflow/lib/common/view.py
dagflow/lib/common/view_concat.py
dagflow/lib/integration/__init__.py
dagflow/lib/integration/integrator.py
dagflow/lib/integration/integrator_core.py
dagflow/lib/integration/integrator_sampler.py
dagflow/lib/interpolation/__init__.py
dagmodelling-0.9.4.dist-info/licenses/LICENSE
dagmodelling-0.9.4.dist-info/METADATA
dagmodelling-0.9.4.dist-info/WHEEL
dagmodelling-0.9.4.dist-info/top_level.txt
dagmodelling-0.9.4.dist-info/RECORD
