Metadata-Version: 2.4
Name: dagmodelling
Version: 0.9.4
Summary: The DAGFlow package is a python implementation of the dataflow programming with the lazy graph evaluation.
Author-email: DAGFlow Team <dagflow@jinr.ru>
Maintainer-email: DAGFlow Team <dagflow@jinr.ru>
License-Expression: MIT
Project-URL: homepage, https://github.com/dagflow-team/dag-flow
Project-URL: repository, https://github.com/dagflow-team/dag-flow
Project-URL: documentation, https://github.com/dagflow-team/dag-flow/wiki
Project-URL: DAGFlow Team, https://github.com/dagflow-team
Requires-Python: >=3.11
License-File: LICENSE
Requires-Dist: contextlib2
Requires-Dist: h5py
Requires-Dist: latexdatax
Requires-Dist: matplotlib
Requires-Dist: numba
Requires-Dist: numpy
Requires-Dist: ordered-set
Requires-Dist: pandas
Requires-Dist: pygraphviz
Requires-Dist: pyyaml
Requires-Dist: schema
Requires-Dist: scipy
Requires-Dist: tabulate
Requires-Dist: uproot
Requires-Dist: plotille
Requires-Dist: nestedmapping
Provides-Extra: dev
Requires-Dist: pytest; extra == "dev"
Requires-Dist: pytest-cov; extra == "dev"
Requires-Dist: coverage; extra == "dev"
Dynamic: license-file
